pycheck/__init__.py
pycheck/check_all.py
pycheck/check_all.pyi
pycheck/check_any.py
pycheck/check_any.pyi
pycheck/check_core.py
pycheck/check_utils.py
py_check-1.2.1.dist-info/LICENSE
py_check-1.2.1.dist-info/METADATA
py_check-1.2.1.dist-info/WHEEL
py_check-1.2.1.dist-info/top_level.txt
py_check-1.2.1.dist-info/RECORD
