Metadata-Version: 2.1
Name: py-check
Version: 1.2.1
Summary: Python Micro check library
Home-page: https://github.com/arlenxuzj/py-check
Author: ArlenX
Author-email: arlenxuzj@gmail.com
License: MIT
Keywords: python python3 types check checker library
Platform: UNKNOWN
Classifier: Development Status :: 5 - Production/Stable
Classifier: Intended Audience :: Developers
Classifier: License :: OSI Approved :: MIT License
Classifier: Operating System :: OS Independent
Classifier: Programming Language :: Python :: 3
Classifier: Programming Language :: Python :: 3.6
Classifier: Programming Language :: Python :: 3.7
Classifier: Programming Language :: Python :: 3.8
Requires-Python: >=3.6, <4
